profile_this/__init__.py
profile_this/core.py
profile_this-0.1.10.dist-info/LICENSE
profile_this-0.1.10.dist-info/METADATA
profile_this-0.1.10.dist-info/WHEEL
profile_this-0.1.10.dist-info/RECORD
