Metadata-Version: 2.3
Name: profile-this
Version: 0.1.10
Summary: A stupid simple memory profiler.
License: MIT
Author: Mike Letts
Author-email: lettsmt@gmail.com
Maintainer: Mike Letts
Maintainer-email: lettsmt@gmail.com
Requires-Python: >=3.13
Classifier: License :: OSI Approved :: MIT License
Classifier: Programming Language :: Python :: 3
Classifier: Programming Language :: Python :: 3.13
Requires-Dist: matplotlib (>=3.10.3,<4.0.0)
Requires-Dist: mplcyberpunk (>=0.7.6,<0.8.0)
Requires-Dist: psutil (>=7.0.0,<8.0.0)
Requires-Dist: seaborn (>=0.13.2,<0.14.0)
Project-URL: Repository, https://github.com/michaelthomasletts/profile-this
